{
    "Eula": {
        "name": "Eula",
        "name_ru": "Эола",
        "element": "Cryo",
        "weapon": "Claymore",
        "rarity": "5",
        "briefly": "Рыцарь Морская пена из старинного рода аристократов Мондштадта, капитан разведывательного отряда рыцарей Ордо Фавониус. Будучи потомком древней аристократии, она присоединилась к рыцарям Ордо Фавониус, их заклятым врагам. Причины этого поступка и по сей день остаются загадкой для всего Мондштадта.",
        "constellation": "Морская Пена",
        "region": "Мондштадт",
        "description": "При попадании по врагу Эола получает Холодное сердце, усиливающее её защиту и сопротивление прерыванию. Эффект может складываться до двух раз.\nПри долгом нажатии элементального навыка Холодное сердце превращается в один Меч вихря, который наносит врагам поблизости урон, снижая их физическое и Крио сопротивление.\nВзрыв стихии Эолы создаёт Меч света. Энергией Меч света питают обычные атаки, элементальные навыки и взрыв стихии Эолы.\nЧерез несколько секунд Меч света наносит врагам поблизости физический урон, размер которого зависит от накопленной им энергии.",
        "skills": [
            {
                "skill_name": "Фехтовальный стиль Фавония: Знать",
                "skill_desc": "Обычная атака:До пяти рубящих ударов мечом.Заряженная атака:Совершает усиленную серию ударов мечомПоследний удар серии наносит дополнительный урон.Атака в падении:Стремительно падает на землю, атакуя всех врагов на пути. Приземлившись, наносит урон по площади."
            },
            {
                "skill_name": "Ледяной прибой",
                "skill_desc": "Ледяной воздух, стремительный меч.\nБыстрое нажатие:\nБыстрый взмах, который наносит Крио урон. При попадании по врагу Эола получает один уровень Холодного сердца. Складывается до 2 раз, может возникнуть 1 раз в 0.3 сек.\nХолодное сердце:\nПовышает сопротивление прерыванию и защиту Эолы.\nДолгое нажатие:\nВсе Холодные сердца расходуются, и Эола наносит Крио урон по площади врагам впереди. Холодные сердца снижают физическое и Крио сопротивление окружающих врагов. Каждое израсходованное Холодное сердце превращается в один Меч вихря, который наносит Крио урон врагам поблизости."
            },
            {
                "skill_name": "Сумеречный меч",
                "skill_desc": "Эола яростно взмахивает мечом, нанося окружающим врагам Крио урон и создавая Меч света, который следует за ней до 7 сек.\nПока Меч света существует, он повышает сопротивление прерыванию Эолы. Когда обычные атаки, элементальные навыки и взрывы стихии Эолы наносят врагам урон, Меч света получает энергию. Он может получить максимум одну единицу каждые 0.1 сек. Когда длительность Меча света заканчивается, он падает и взрывается, нанося врагам поблизости физический урон.  Наносимый урон зависит от количества накопленной Мечом света энергии.\nМеч света взрывается сам при смене персонажа."
            },
            {
                "skill_name": "Дрожащий иней",
                "skill_desc": "Если при долгом нажатии навыка Ледяной прибой за раз тратится два уровня Холодного сердца, то появляется сломанный Меч света, который тут же взрывается и в виде физического урона наносит 50% от базового урона Меча света, создаваемого Сумеречным мечом."
            },
            {
                "skill_name": "Прилив войны",
                "skill_desc": "Использование Сумеречного меча сбрасывает откат Ледяного прибоя и даёт Эоле один уровень Холодного сердца."
            },
            {
                "skill_name": "Рефлексия аристократа",
                "skill_desc": "При создании материалов повышения талантов персонажей есть 10% шанс создать дополнительный предмет."
            }
        ],
        "constellations": [
            {
                "const_name": "Иллюзия прибоя",
                "const_desc": "Когда Эола тратит Холодное сердце во время Ледяного прибоя её бонус физического урона увеличивается на 30% в течение 6 сек.Каждое потраченное Холодное сердце увеличивает длительность эффекта на 6 сек.Длительность не может превышать 18 сек."
            },
            {
                "const_name": "Дева морской пены",
                "const_desc": "Уменьшает время отката заряженного режима Ледяного прибоя, делая его равным времени отката незаряженного варианта."
            },
            {
                "const_name": "Кровь Лоуренсов",
                "const_desc": "Увеличивает уровень навыка Сумеречный меч на 3.Макс. уровень: 15"
            },
            {
                "const_name": "Упрямство толпы",
                "const_desc": "Меч света наносит на 25% больше урона против врагов с HP ниже 50%."
            },
            {
                "const_name": "Рыцарская суть",
                "const_desc": "Увеличивает уровень навыка Ледяной прибой на 3.Макс. уровень: 15"
            },
            {
                "const_name": "Долг благородных",
                "const_desc": "Меч света, который создаёт талант Сумеречный меч, сразу получает 5 единиц энергии. Когда обычная атака, элементальный навык или взрыв стихии даёт Мечу света энергию, у него есть 50% шанс дополнительно получить ещё одну единицу энергии."
            }
        ],
        "elevation": [
            {
                "0": {
                    "hp": "1 029",
                    "atc": "26",
                    "def": "58",
                    "sub": {
                        "attr": "Крит. урон",
                        "par": "—"
                    }
                },
                "20": {
                    "hp": "2 670",
                    "atc": "69",
                    "def": " 151",
                    "sub": {
                        "attr": "Крит. урон",
                        "par": "—"
                    }
                }
            },
            {
                "20+": {
                    "hp": "3 553",
                    "atc": "91",
                    "def": " 201",
                    "sub": {
                        "attr": "Крит. урон",
                        "par": "—"
                    }
                },
                "40": {
                    "hp": "5 317",
                    "atc": " 137",
                    "def": " 301",
                    "sub": {
                        "attr": "Крит. урон",
                        "par": "—"
                    }
                }
            },
            {
                "40+": {
                    "hp": "5 944",
                    "atc": " 153",
                    "def": " 337",
                    "sub": {
                        "attr": "Крит. урон",
                        "par": "9.6%"
                    }
                },
                "50": {
                    "hp": "6 839",
                    "atc": " 176",
                    "def": " 388",
                    "sub": {
                        "attr": "Крит. урон",
                        "par": "9.6%"
                    }
                }
            },
            {
                "50+": {
                    "hp": "7 675",
                    "atc": " 198",
                    "def": " 435",
                    "sub": {
                        "attr": "Крит. урон",
                        "par": "19.2%"
                    }
                },
                "60": {
                    "hp": "8 579",
                    "atc": " 221",
                    "def": " 487",
                    "sub": {
                        "attr": "Крит. урон",
                        "par": "19.2%"
                    }
                }
            },
            {
                "60+": {
                    "hp": "9 206",
                    "atc": " 238",
                    "def": " 522",
                    "sub": {
                        "attr": "Крит. урон",
                        "par": "19.2%"
                    }
                },
                "70": {
                    "hp": "10 118",
                    "atc": " 261",
                    "def": " 574",
                    "sub": {
                        "attr": "Крит. урон",
                        "par": "19.2%"
                    }
                }
            },
            {
                "70+": {
                    "hp": "10 746",
                    "atc": " 277",
                    "def": " 610",
                    "sub": {
                        "attr": "Крит. урон",
                        "par": "28.8%"
                    }
                },
                "80": {
                    "hp": "11 668",
                    "atc": " 301",
                    "def": " 662",
                    "sub": {
                        "attr": "Крит. урон",
                        "par": "28.8%"
                    }
                }
            },
            {
                "80+": {
                    "hp": "12 295",
                    "atc": " 317",
                    "def": " 698",
                    "sub": {
                        "attr": "Крит. урон",
                        "par": "38.4%"
                    }
                },
                "90": {
                    "hp": "13 225",
                    "atc": " 342",
                    "def": " 750",
                    "sub": {
                        "attr": "Крит. урон",
                        "par": "38.4%"
                    }
                }
            }
        ],
        "mat": {
            "0-1": {
                "0": {
                    "name": "Mora",
                    "len": "20,000"
                },
                "1": {
                    "name": "Shivada Jade Sliver",
                    "len": "1"
                },
                "2": {
                    "name": "Dandelion Seed",
                    "len": "3"
                },
                "3": {
                    "name": "Damaged Mask",
                    "len": "3"
                }
            },
            "1-2": {
                "0": {
                    "name": "Mora",
                    "len": "40,000"
                },
                "1": {
                    "name": "Crystalline Bloom",
                    "len": "2"
                },
                "2": {
                    "name": "Shivada Jade Fragment",
                    "len": "3"
                },
                "3": {
                    "name": "Dandelion Seed",
                    "len": "10"
                },
                "4": {
                    "name": "Damaged Mask",
                    "len": "15"
                }
            },
            "2-3": {
                "0": {
                    "name": "Mora",
                    "len": "60,000"
                },
                "1": {
                    "name": "Crystalline Bloom",
                    "len": "4"
                },
                "2": {
                    "name": "Shivada Jade Fragment",
                    "len": "6"
                },
                "3": {
                    "name": "Dandelion Seed",
                    "len": "20"
                },
                "4": {
                    "name": "Stained Mask",
                    "len": "12"
                }
            },
            "3-4": {
                "0": {
                    "name": "Mora",
                    "len": "80,000"
                },
                "1": {
                    "name": "Crystalline Bloom",
                    "len": "8"
                },
                "2": {
                    "name": "Shivada Jade Chunk",
                    "len": "3"
                },
                "3": {
                    "name": "Dandelion Seed",
                    "len": "30"
                },
                "4": {
                    "name": "Stained Mask",
                    "len": "18"
                }
            },
            "4-5": {
                "0": {
                    "name": "Mora",
                    "len": "100,000"
                },
                "1": {
                    "name": "Crystalline Bloom",
                    "len": "12"
                },
                "2": {
                    "name": "Shivada Jade Chunk",
                    "len": "6"
                },
                "3": {
                    "name": "Dandelion Seed",
                    "len": "45"
                },
                "4": {
                    "name": "Ominous Mask",
                    "len": "12"
                }
            },
            "5-6": {
                "0": {
                    "name": "Mora",
                    "len": "120,000"
                },
                "1": {
                    "name": "Crystalline Bloom",
                    "len": "20"
                },
                "2": {
                    "name": "Shivada Jade Gemstone",
                    "len": "6"
                },
                "3": {
                    "name": "Dandelion Seed",
                    "len": "60"
                },
                "4": {
                    "name": "Ominous Mask",
                    "len": "24"
                }
            }
        }
    }
}